QuantumCheck/__init__.py
QuantumCheck/main.py
QuantumCheck/powerbi_evaluator.py
QuantumCheck/prompts.py
QuantumCheck/python_evaluator.py
QuantumCheck/sql_evaluator.py
QuantumCheck/ssis_evaluator.py
quantumchecker-0.5.0.dist-info/METADATA
quantumchecker-0.5.0.dist-info/WHEEL
quantumchecker-0.5.0.dist-info/top_level.txt
quantumchecker-0.5.0.dist-info/RECORD
