Metadata-Version: 2.4
Name: QuantumChecker
Version: 0.5.0
Summary: A package to evaluate homework submissions in Python, SQL, PowerBI, and SSIS.
Author: Qobiljon
Author-email: qobiljonkhayrullayev@gmail.com
Classifier: Programming Language :: Python :: 3
Classifier: License :: OSI Approved :: MIT License
Classifier: Operating System :: OS Independent
Requires-Python: >=3.6
Requires-Dist: requests>=2.31.0
Requires-Dist: tenacity>=8.2.3
Requires-Dist: pdf2image>=1.16.3
Requires-Dist: python-dotenv>=1.0.0
Requires-Dist: Pillow>=10.0.0
Requires-Dist: PyPDF2>=3.0.1
Dynamic: author
Dynamic: author-email
Dynamic: classifier
Dynamic: description
Dynamic: description-content-type
Dynamic: requires-dist
Dynamic: requires-python
Dynamic: summary
